{
	"id": 4,
	"nombre": "Chubut",
	"ciudades": [
		{
			"id": "1791",
			"nombre": "Acceso Norte"
		},
		{
			"id": "1848",
			"nombre": "Aldea Apeleg"
		},
		{
			"id": "1849",
			"nombre": "Aldea Beleiro"
		},
		{
			"id": "1833",
			"nombre": "Aldea Epulef"
		},
		{
			"id": "1817",
			"nombre": "Aldea Escolar"
		},
		{
			"id": "1850",
			"nombre": "Alto Rio Senguer"
		},
		{
			"id": "1863",
			"nombre": "Arroyo Verde"
		},
		{
			"id": "1789",
			"nombre": "Astra"
		},
		{
			"id": "1790",
			"nombre": "Bahia Bustamante"
		},
		{
			"id": "1792",
			"nombre": "Barrio Caleta Cordova"
		},
		{
			"id": "1793",
			"nombre": "Barrio Caleta Olivares"
		},
		{
			"id": "1794",
			"nombre": "Barrio Castelli"
		},
		{
			"id": "1795",
			"nombre": "Barrio Ciudadela"
		},
		{
			"id": "1796",
			"nombre": "Barrio Gasoducto"
		},
		{
			"id": "1797",
			"nombre": "Barrio GÜEMES"
		},
		{
			"id": "1798",
			"nombre": "Barrio Laprida"
		},
		{
			"id": "1799",
			"nombre": "Barrio Manantial Rosales"
		},
		{
			"id": "1800",
			"nombre": "Barrio Militar - Aeropuerto Militar"
		},
		{
			"id": "1801",
			"nombre": "Barrio Prospero Palazzo"
		},
		{
			"id": "1802",
			"nombre": "Barrio Restinga Ali"
		},
		{
			"id": "1803",
			"nombre": "Barrio Rodriguez Peña"
		},
		{
			"id": "1804",
			"nombre": "Barrio Saavedra"
		},
		{
			"id": "1805",
			"nombre": "Barrio Sarmiento"
		},
		{
			"id": "1807",
			"nombre": "Barrio Villa S.U.P.E."
		},
		{
			"id": "1806",
			"nombre": "Barrio 25 De Mayo"
		},
		{
			"id": "1828",
			"nombre": "Blancuntre"
		},
		{
			"id": "1855",
			"nombre": "Buen Pasto"
		},
		{
			"id": "1779",
			"nombre": "Buenos Aires Chico"
		},
		{
			"id": "1815",
			"nombre": "Camarones"
		},
		{
			"id": "1834",
			"nombre": "Carrenleufu"
		},
		{
			"id": "1840",
			"nombre": "Cerro Condor"
		},
		{
			"id": "1780",
			"nombre": "Cholila"
		},
		{
			"id": "1835",
			"nombre": "Colan Conhue"
		},
		{
			"id": "1808",
			"nombre": "Comodoro Rivadavia"
		},
		{
			"id": "1818",
			"nombre": "Corcovado"
		},
		{
			"id": "1781",
			"nombre": "Cushamen Centro"
		},
		{
			"id": "1813",
			"nombre": "Diadema Argentina"
		},
		{
			"id": "1824",
			"nombre": "Dique Florentino Ameghino"
		},
		{
			"id": "1851",
			"nombre": "Doctor Ricardo Rojas"
		},
		{
			"id": "1825",
			"nombre": "Dolavon"
		},
		{
			"id": "1829",
			"nombre": "El Escorial"
		},
		{
			"id": "1782",
			"nombre": "El Hoyo"
		},
		{
			"id": "1783",
			"nombre": "El Maiten"
		},
		{
			"id": "1838",
			"nombre": "El Mirasol"
		},
		{
			"id": "1784",
			"nombre": "Epuyen"
		},
		{
			"id": "1819",
			"nombre": "Esquel"
		},
		{
			"id": "1852",
			"nombre": "Facundo"
		},
		{
			"id": "1857",
			"nombre": "Frontera De Rio Pico"
		},
		{
			"id": "1826",
			"nombre": "Gaiman"
		},
		{
			"id": "1861",
			"nombre": "Gan Gan"
		},
		{
			"id": "1816",
			"nombre": "Garayalde"
		},
		{
			"id": "1830",
			"nombre": "Gastre"
		},
		{
			"id": "1858",
			"nombre": "Gobernador Costa"
		},
		{
			"id": "1785",
			"nombre": "Gualjaina"
		},
		{
			"id": "1859",
			"nombre": "Jose De San Martin"
		},
		{
			"id": "1811",
			"nombre": "Km. 11 - Cuarteles"
		},
		{
			"id": "1812",
			"nombre": "Km. 3 - General Mosconi"
		},
		{
			"id": "1809",
			"nombre": "Km. 5 - Presidente Ortiz"
		},
		{
			"id": "1810",
			"nombre": "Km. 8 - Don Bosco"
		},
		{
			"id": "1853",
			"nombre": "Lago Blanco"
		},
		{
			"id": "1786",
			"nombre": "Lago Epuyen"
		},
		{
			"id": "1787",
			"nombre": "Lago Puelo"
		},
		{
			"id": "1820",
			"nombre": "Lago Rosario"
		},
		{
			"id": "1831",
			"nombre": "Lagunita Salada"
		},
		{
			"id": "1839",
			"nombre": "Las Plumas"
		},
		{
			"id": "1788",
			"nombre": "Leleque"
		},
		{
			"id": "1841",
			"nombre": "Los Altares"
		},
		{
			"id": "1821",
			"nombre": "Los Cipreses"
		},
		{
			"id": "1842",
			"nombre": "Paso De Indios"
		},
		{
			"id": "1836",
			"nombre": "Paso Del Sapo"
		},
		{
			"id": "1843",
			"nombre": "Playa Magagna"
		},
		{
			"id": "1844",
			"nombre": "Playa Union"
		},
		{
			"id": "1864",
			"nombre": "Puerto Madryn"
		},
		{
			"id": "1865",
			"nombre": "Puerto Piramide"
		},
		{
			"id": "1845",
			"nombre": "Puerto Rawson"
		},
		{
			"id": "1866",
			"nombre": "Quinta El Mirador"
		},
		{
			"id": "1814",
			"nombre": "Rada Tilly"
		},
		{
			"id": "1846",
			"nombre": "Rawson"
		},
		{
			"id": "1854",
			"nombre": "Rio Mayo"
		},
		{
			"id": "1860",
			"nombre": "Rio Pico"
		},
		{
			"id": "1856",
			"nombre": "Sarmiento"
		},
		{
			"id": "1837",
			"nombre": "Tecka"
		},
		{
			"id": "1862",
			"nombre": "Telsen"
		},
		{
			"id": "1847",
			"nombre": "Trelew"
		},
		{
			"id": "1822",
			"nombre": "Trevelin"
		},
		{
			"id": "1823",
			"nombre": "Villa Futalaufquen"
		},
		{
			"id": "1832",
			"nombre": "Yala Laubat"
		},
		{
			"id": "1827",
			"nombre": "28 De Julio"
		}
	]
}