{
  "id": 8,
  "nombre": "Formosa",
  "ciudades": [
    {
      "id": "2057",
      "nombre": "Banco Payagua"
    },
    {
      "id": "2064",
      "nombre": "Bartolome De Las Casas"
    },
    {
      "id": "2081",
      "nombre": "Buena Vista"
    },
    {
      "id": "2087",
      "nombre": "Clorinda"
    },
    {
      "id": "2095",
      "nombre": "Colonia Campo Villafañe"
    },
    {
      "id": "2049",
      "nombre": "Colonia Pastoril"
    },
    {
      "id": "2065",
      "nombre": "Colonia Sarmiento"
    },
    {
      "id": "2066",
      "nombre": "Comandante Fontana"
    },
    {
      "id": "2096",
      "nombre": "El Colorado"
    },
    {
      "id": "2082",
      "nombre": "El Espinillo"
    },
    {
      "id": "2100",
      "nombre": "El Potrillo"
    },
    {
      "id": "2067",
      "nombre": "El Recreo"
    },
    {
      "id": "2068",
      "nombre": "Estanislao Del Campo"
    },
    {
      "id": "2050",
      "nombre": "Formosa"
    },
    {
      "id": "2069",
      "nombre": "Fortin Cabo 1º Lugones"
    },
    {
      "id": "2070",
      "nombre": "Fortin Sargento 1º Leyes"
    },
    {
      "id": "2058",
      "nombre": "General Lucio V. Mansilla"
    },
    {
      "id": "2101",
      "nombre": "General Mosconi"
    },
    {
      "id": "2051",
      "nombre": "Gran Guardia"
    },
    {
      "id": "2059",
      "nombre": "Herradura"
    },
    {
      "id": "2071",
      "nombre": "Ibarreta"
    },
    {
      "id": "2063",
      "nombre": "Ingeniero Guillermo N. Juarez"
    },
    {
      "id": "2072",
      "nombre": "Juan G. Bazan"
    },
    {
      "id": "2088",
      "nombre": "Laguna Blanca"
    },
    {
      "id": "2083",
      "nombre": "Laguna Gallo"
    },
    {
      "id": "2089",
      "nombre": "Laguna Naick-Neck"
    },
    {
      "id": "2045",
      "nombre": "Laguna Yema"
    },
    {
      "id": "2073",
      "nombre": "Las Lomitas"
    },
    {
      "id": "2046",
      "nombre": "Los Chiriguanos"
    },
    {
      "id": "2052",
      "nombre": "Mariano Boedo"
    },
    {
      "id": "2084",
      "nombre": "Mision Tacaagle"
    },
    {
      "id": "2053",
      "nombre": "Mojon De Fierro"
    },
    {
      "id": "2090",
      "nombre": "Palma Sola"
    },
    {
      "id": "2097",
      "nombre": "Palo Santo"
    },
    {
      "id": "2098",
      "nombre": "Pirane"
    },
    {
      "id": "2085",
      "nombre": "Porton Negro"
    },
    {
      "id": "2074",
      "nombre": "Posta Cambio Zalazar"
    },
    {
      "id": "2047",
      "nombre": "Pozo De Maza"
    },
    {
      "id": "2048",
      "nombre": "Pozo Del Mortero"
    },
    {
      "id": "2075",
      "nombre": "Pozo Del Tigre"
    },
    {
      "id": "2091",
      "nombre": "Puerto Pilcomayo"
    },
    {
      "id": "2092",
      "nombre": "Riacho He-He"
    },
    {
      "id": "2093",
      "nombre": "Riacho Negro"
    },
    {
      "id": "2060",
      "nombre": "San Francisco De Laishi"
    },
    {
      "id": "2054",
      "nombre": "San Hilario"
    },
    {
      "id": "2076",
      "nombre": "San Martin I"
    },
    {
      "id": "2077",
      "nombre": "San Martin Ii"
    },
    {
      "id": "2094",
      "nombre": "Siete Palmas"
    },
    {
      "id": "2078",
      "nombre": "Subteniente Perin"
    },
    {
      "id": "2061",
      "nombre": "Tatane"
    },
    {
      "id": "2086",
      "nombre": "Tres Lagunas"
    },
    {
      "id": "2055",
      "nombre": "Villa Del Carmen"
    },
    {
      "id": "2062",
      "nombre": "Villa Escolar"
    },
    {
      "id": "2079",
      "nombre": "Villa General GÜEMES"
    },
    {
      "id": "2080",
      "nombre": "Villa General Manuel Belgrano"
    },
    {
      "id": "2099",
      "nombre": "Villa Kilometro 213"
    },
    {
      "id": "2056",
      "nombre": "Villa Trinidad"
    }
  ]
}